License.txt
MANIFEST.in
README.md
setup.py
pyi/__init__.py
pyi/cli.py
pyi/core.py
pyi.egg-info/PKG-INFO
pyi.egg-info/SOURCES.txt
pyi.egg-info/dependency_links.txt
pyi.egg-info/requires.txt
pyi.egg-info/top_level.txt
scripts/pyi