Metadata-Version: 1.1
Name: pyi
Version: 0.1.0
Summary: UNKNOWN
Home-page: http://github.com/grokzen/pyi
Author: Johan Andersson
Author-email: Grokzen@gmail.com
License: MIT
Platform: UNKNOWN
Classifier: Development Status :: 5 - Production/Stable
Classifier: Intended Audience :: Developers
Classifier: Operating System :: OS Independent
Classifier: License :: OSI Approved :: MIT License
Classifier: Environment :: Console
Classifier: Programming Language :: Python
Classifier: Programming Language :: Python :: 2.7
